easy_paddle_ocr/__init__.py
easy_paddle_ocr/algorithm/__init__.py
easy_paddle_ocr/algorithm/text_recognizer.py
easy_paddle_ocr/algorithm/weights/__init__.py
easy_paddle_ocr/algorithm/weights/dictionary.txt
easy_paddle_ocr/algorithm/weights/inference.pdiparams
easy_paddle_ocr/algorithm/weights/inference.pdiparams.info
easy_paddle_ocr/algorithm/weights/inference.pdmodel
easy_paddle_ocr/ppocr/__init__.py
easy_paddle_ocr/ppocr/postprocess/__init__.py
easy_paddle_ocr/ppocr/postprocess/rec_postprocess.py
easy_paddle_ocr/ppocr/utils/__init__.py
easy_paddle_ocr/ppocr/utils/utility.py
easy_paddle_ocr/tools/__init__.py
easy_paddle_ocr/tools/infer/__init__.py
easy_paddle_ocr/tools/infer/predict_rec.py
easy_paddle_ocr/tools/infer/utility.py
easy_paddle_ocr-0.0.5.dist-info/METADATA
easy_paddle_ocr-0.0.5.dist-info/WHEEL
easy_paddle_ocr-0.0.5.dist-info/top_level.txt
easy_paddle_ocr-0.0.5.dist-info/RECORD
