Metadata-Version: 2.1
Name: easy-paddle-ocr
Version: 0.0.5
Summary: This a clean and easy-to-use implementation of Paddle OCR. Made with ❤️ by Theos AI.
Home-page: https://theos.ai
Author: Theos AI
Author-email: contact@theos.ai
License: Other/Proprietary License
Keywords: theos
Classifier: Development Status :: 3 - Alpha
Classifier: Intended Audience :: Developers
Classifier: Topic :: Software Development :: Build Tools
Classifier: License :: Other/Proprietary License
Classifier: Programming Language :: Python :: 3
Requires-Dist: shapely
Requires-Dist: scikit-image
Requires-Dist: imgaug
Requires-Dist: pyclipper
Requires-Dist: lmdb
Requires-Dist: tqdm
Requires-Dist: numpy
Requires-Dist: visualdl
Requires-Dist: rapidfuzz
Requires-Dist: opencv-python (==4.6.0.66)
Requires-Dist: opencv-contrib-python (==4.6.0.66)
Requires-Dist: cython
Requires-Dist: lxml
Requires-Dist: premailer
Requires-Dist: openpyxl
Requires-Dist: attrdict
Requires-Dist: Polygon3
Requires-Dist: lanms-neo (==1.0.2)
Requires-Dist: PyMuPDF (<1.21.0)
Requires-Dist: shutup (==0.2.0)
Requires-Dist: paddlepaddle (==2.4.2)
